benchmark_examples/__init__.py
benchmark_examples/autoattack/__init__.py
benchmark_examples/autoattack/base.py
benchmark_examples/autoattack/benchmark.py
benchmark_examples/autoattack/global_config.py
benchmark_examples/autoattack/main.py
benchmark_examples/autoattack/applications/__init__.py
benchmark_examples/autoattack/applications/base.py
benchmark_examples/autoattack/applications/image/__init__.py
benchmark_examples/autoattack/applications/image/cifar10/__init__.py
benchmark_examples/autoattack/applications/image/cifar10/cifar10_base.py
benchmark_examples/autoattack/applications/image/cifar10/data_utils.py
benchmark_examples/autoattack/applications/image/cifar10/cnn/__init__.py
benchmark_examples/autoattack/applications/image/cifar10/cnn/cifar10_cnn.py
benchmark_examples/autoattack/applications/image/cifar10/resnet18/__init__.py
benchmark_examples/autoattack/applications/image/cifar10/resnet18/cifar10_resnet18.py
benchmark_examples/autoattack/applications/image/cifar10/resnet20/__init__.py
benchmark_examples/autoattack/applications/image/cifar10/resnet20/cifar10_resnet20.py
benchmark_examples/autoattack/applications/image/cifar10/vgg16/__init__.py
benchmark_examples/autoattack/applications/image/cifar10/vgg16/cifar10_vgg16.py
benchmark_examples/autoattack/applications/image/mnist/__init__.py
benchmark_examples/autoattack/applications/image/mnist/mnist_base.py
benchmark_examples/autoattack/applications/image/mnist/resnet18/__init__.py
benchmark_examples/autoattack/applications/image/mnist/resnet18/mnist_resnet18.py
benchmark_examples/autoattack/applications/image/mnist/vgg16/__init__.py
benchmark_examples/autoattack/applications/image/mnist/vgg16/mnist_vgg16.py
benchmark_examples/autoattack/applications/recommendation/__init__.py
benchmark_examples/autoattack/applications/recommendation/criteo/__init__.py
benchmark_examples/autoattack/applications/recommendation/criteo/criteo_base.py
secretflow_lite-1.13.0b0.dist-info/licenses/LICENSE
secretflow_lite-1.13.0b0.dist-info/METADATA
secretflow_lite-1.13.0b0.dist-info/WHEEL
secretflow_lite-1.13.0b0.dist-info/entry_points.txt
secretflow_lite-1.13.0b0.dist-info/top_level.txt
secretflow_lite-1.13.0b0.dist-info/RECORD
