Metadata-Version: 2.4
Name: secretflow-lite
Version: 1.13.0b0
Summary: SecretFlow Lite
Home-page: https://github.com/secretflow/secretflow
Author: SCI Center
Author-email: secretflow-contact@service.alipay.com
License: Apache 2.0
License-File: LICENSE
Requires-Dist: click
Requires-Dist: grpcio>=1.56.2
Requires-Dist: jax[cpu]<=0.4.26,>=0.4.16
Requires-Dist: jaxlib<=0.4.26,>=0.4.16
Requires-Dist: kuscia==0.0.3b0
Requires-Dist: secretflow-dataproxy==0.5.0.dev20250416
Requires-Dist: numpy
Requires-Dist: pandas==1.5.3
Requires-Dist: protobuf<5,>=4
Requires-Dist: pyarrow==14.0.2
Requires-Dist: duckdb==1.0.0
Requires-Dist: aiobotocore==2.17.0
Requires-Dist: s3fs==2024.2.0
Requires-Dist: scikit-learn==1.5.2
Requires-Dist: sdc-apis==0.1.0.dev240320; platform_machine == "x86_64"
Requires-Dist: sdc-sdk==0.1.0.dev240320; platform_machine == "x86_64"
Requires-Dist: aiohttp<4,>=3.9.4
Requires-Dist: setuptools==75.8.0
Requires-Dist: spu==0.9.4.dev20250618
Requires-Dist: sf-sml==0.1.0.dev20250623
Requires-Dist: sf-heu==0.6.0.dev20250514
Requires-Dist: secretflow_serving_lib==0.10.0.dev20250414
Requires-Dist: sqlglot==25.5.1
Requires-Dist: requests==2.32.3
Requires-Dist: secretflow-spec==1.1.0b0
Requires-Dist: multiprocess==0.70.18
Provides-Extra: dev
Requires-Dist: pylint; extra == "dev"
Dynamic: author
Dynamic: author-email
Dynamic: description
Dynamic: description-content-type
Dynamic: home-page
Dynamic: license
Dynamic: license-file
Dynamic: provides-extra
Dynamic: requires-dist
Dynamic: summary
